[
  {
    "order_count": 45162,
    "avg_delivery_duration_min": 26.298,
    "median_delivery_duration_min": 26.0,
    "p75_delivery_duration_min": 32.0,
    "avg_distance_km": 9.735,
    "delay_rate": 0.247,
    "scene_id": "overall",
    "risk_score": 0.631,
    "delay_threshold_min": 32.0,
    "source_filter": "all clean orders",
    "description": "全量清洗订单。"
  },
  {
    "order_count": 7238,
    "avg_delivery_duration_min": 21.855,
    "median_delivery_duration_min": 20.0,
    "p75_delivery_duration_min": 26.0,
    "avg_distance_km": 9.626,
    "delay_rate": 0.102,
    "scene_id": "sunny",
    "risk_score": 0.44,
    "delay_threshold_min": 32.0,
    "source_filter": "weather == Sunny",
    "description": "晴天订单，用作天气基准。"
  },
  {
    "order_count": 7604,
    "avg_delivery_duration_min": 28.933,
    "median_delivery_duration_min": 29.0,
    "p75_delivery_duration_min": 37.0,
    "avg_distance_km": 9.77,
    "delay_rate": 0.382,
    "scene_id": "fog",
    "risk_score": 0.619,
    "delay_threshold_min": 32.0,
    "source_filter": "weather == Fog",
    "description": "雾天订单。"
  },
  {
    "order_count": 7544,
    "avg_delivery_duration_min": 25.866,
    "median_delivery_duration_min": 26.0,
    "p75_delivery_duration_min": 31.0,
    "avg_distance_km": 9.749,
    "delay_rate": 0.203,
    "scene_id": "stormy",
    "risk_score": 0.522,
    "delay_threshold_min": 32.0,
    "source_filter": "weather == Stormy",
    "description": "雷暴天气订单。"
  },
  {
    "order_count": 7442,
    "avg_delivery_duration_min": 25.872,
    "median_delivery_duration_min": 26.0,
    "p75_delivery_duration_min": 31.0,
    "avg_distance_km": 9.686,
    "delay_rate": 0.202,
    "scene_id": "sandstorms",
    "risk_score": 0.521,
    "delay_threshold_min": 32.0,
    "source_filter": "weather == Sandstorms",
    "description": "沙尘天气订单。"
  },
  {
    "order_count": 7485,
    "avg_delivery_duration_min": 28.922,
    "median_delivery_duration_min": 28.0,
    "p75_delivery_duration_min": 37.0,
    "avg_distance_km": 9.802,
    "delay_rate": 0.375,
    "scene_id": "cloudy",
    "risk_score": 0.616,
    "delay_threshold_min": 32.0,
    "source_filter": "weather == Cloudy",
    "description": "多云天气订单。"
  },
  {
    "order_count": 7382,
    "avg_delivery_duration_min": 26.128,
    "median_delivery_duration_min": 26.0,
    "p75_delivery_duration_min": 31.0,
    "avg_distance_km": 9.776,
    "delay_rate": 0.212,
    "scene_id": "windy",
    "risk_score": 0.528,
    "delay_threshold_min": 32.0,
    "source_filter": "weather == Windy",
    "description": "大风天气订单。"
  }
]
